pyhomely/__init__.py
pyhomely/client.py
pyhomely/const.py
pyhomely/exceptions.py
pyhomely/types.py
pyhomely-0.2.2.dist-info/LICENSE
pyhomely-0.2.2.dist-info/METADATA
pyhomely-0.2.2.dist-info/WHEEL
pyhomely-0.2.2.dist-info/RECORD
