Metadata-Version: 2.1
Name: pyhomely
Version: 0.2.2
Summary: 
Home-page: https://github.com/ludeeus/pyhomely
License: MIT
Author: Ludeeus
Author-email: ludeeus@ludeeus.dev
Maintainer: Ludeeus
Maintainer-email: ludeeus@ludeeus.dev
Requires-Python: >=3.12,<4.0
Classifier: Intended Audience :: Developers
Classifier: License :: OSI Approved :: MIT License
Classifier: Natural Language :: English
Classifier: Programming Language :: Python :: 3
Classifier: Programming Language :: Python :: 3.12
Classifier: Programming Language :: Python :: 3.13
Classifier: Topic :: Software Development :: Libraries :: Python Modules
Requires-Dist: aiohttp (>=3.10,<4.0)
Requires-Dist: python-socketio[asyncio-client] (>=5,<6)
Project-URL: Repository, https://github.com/ludeeus/pyhomely
